src/memory.v
module memory(
    input clk,
    input mem_read,  // read enable
    input mem_write, // write enable
    input [31:0] addr, // address for read/write
    input [31:0] wdata, // data to write
    output[31:0] rdata // data to read
);
    reg [31:0] mem [0:2047]; // 8KB memory (2048 words of 32 bits each)

    // Read operation
    // The two least significant bits of addr indicates the byte's position within its word (byte offset)
    // The upper 11 bits [12:2] indicate which the word it belongs to (word address))
    assign rdata = (mem_read) ? mem[addr[12:2]] : 32'b0; // If read enabled, output the data at the address; else output 0

    // Write operation
    always_ff @(posedge clk) begin 
        if (mem_write) begin 
            mem[addr[12:2]] <= wdata;
        end 
    end 

    // Initialize memory to zero
    initial begin 
        // Initialize all memory to zero first
        for (integer i = 0; i < 2048; i = i + 1) begin
            mem[i] = 32'h00000000;
        end
        
        // Try to load from file, but don't fail if file doesn't exist
        $readmemh("bin/firmware.img", mem); // Load memory from a file
    end 

    // Handle unused address bits (word-aligned memory access)
    // We only use addr[12:2] for word addressing, bits [31:13,1:0] are unused
    wire _unused_ok = 1'b0 && &{1'b0,
                        addr[31:13],  // Upper address bits unused (8KB memory limit)
                        addr[1:0],    // Lower 2 bits unused (word-aligned access)
                        1'b0};
endmodule

src/alu.v
module alu (
    input [31:0] a,
    input [31:0] b,
    input [3:0] alu_control,
    output reg [31:0] result,
    output zero
);
    // Zero flag
    assign zero = (result == 32'b0);

    // ALU control signals
    parameter ALU_AND = 4'b0000;
    parameter ALU_OR  = 4'b0001;
    parameter ALU_ADD = 4'b0010;
    parameter ALU_SUB = 4'b0110;
    parameter ALU_SLT = 4'b0111;
    parameter ALU_NOR = 4'b1100;
    //parameter ALU_NAND = 4'b1101; // Uncomment if NAND is needed
    
    // ALU operations
    always_comb begin
        case (alu_control)
            ALU_AND: result = a & b; // AND
            ALU_OR:  result = a | b; // OR
            ALU_ADD: result = a + b; // ADD
            ALU_SUB: result = a - b; // SUBTRACT
            ALU_SLT: result = (a < b) ? 32'b1 : 32'b0; // SLT (Set Less Than)
            ALU_NOR: result = ~(a | b); // NOR

            default: result = 32'b0; // Default case
        endcase
    end

endmodule

src/register_file.v
module register_file(
    input clk, // clock signal
    input we,  // write enable
    input [4:0] raddr1, // read register address 1
    input [4:0] raddr2, // read register address 2
    input [4:0] waddr,  // write register address
    input [31:0] wdata, // write data
    output [31:0] rdata1, // read data 1
    output [31:0] rdata2  // read data 2
);
    reg [31:0] registers [0:31]; // 32 registers of 32 bits each 

    // read operation 
    assign rdata1 = (raddr1 == 0) ? 32'b0 : registers[raddr1];
    assign rdata2 = (raddr2 == 0) ? 32'b0 : registers[raddr2];

    // write operation 
    // always_ff for sequential logic (flip-flops) only
    // always for combinational logic and sequential logic
    always_ff @(posedge clk) begin 
        if (we && waddr != 0) begin 
            registers[waddr] <= wdata; // write data to the register
        end
    end 

    // Initialize registers to zero
    integer i;
    initial begin
        for (i = 0; i < 32; i = i + 1) begin
            registers[i] = 32'b0; // set all registers to zero
        end
        registers[2] = 32'h8000; // stack pointer x2(sp) initialized to 0x8000
    end
endmodule

src/cpu.v
module cpu(
    input clk,
    input reset
);
    // Internal signals
    // PC signals
    logic [31:0] pc; // Program counter
    logic [31:0] pc_plus4; // PC + 4 for next instruction fetch
    logic [31:0] pc_branch; // Branch target address
    logic [31:0] pc_next; // Next program counter
    
    // Instruction memory signals 
    logic [31:0] instruction; // Current instruction
    
    // Register file signals
    logic        reg_write_enable; // Register write enable, control signal
    logic [4:0]  rs1_addr, rs2_addr, rd_addr; // Register addresses
    logic [31:0] rs1_data, rs2_data, rd_data; // Register file data

    // ALU signals
    logic [31:0] alu_a; // ALU first operand
    logic [31:0] alu_b; // ALU second operand
    logic [3:0]  alu_control; // ALU control signal
    logic [31:0] alu_result; // ALU result
    logic        alu_zero; // ALU zero flag
    
    // Data memory signals
    logic        mem_read_enable; // Data memory read enable, control signal 
    logic        mem_write_enable; // Data memory write enable, control signal
    logic [31:0] mem_rdata; // Data memory read Data

    // Control signals
    logic         branch;  // Branch signal
    logic         mem_to_reg; // Memory to register signal (0: ALU result, 1: Memory data)
    logic  [1:0]  alu_op; // ALU operation type
    logic         alu_src; // ALU source select (0: register, 1: immediate)
    logic  [31:0] imm; // Immediate value
    logic  [6:0]  opcode; // Instruction opcode
    logic  [2:0]  funct3; // Instruction funct3
    logic  [6:0]  funct7; // Instruction funct7

    // Instantiate the instruction memory
    memory instruction_memory(
        .clk(clk),
        .mem_read(1'b1), // Instruction memory is read-only
        .mem_write(1'b0), // No write operation for instruction memory
        .addr(pc),
        .wdata(32'b0), // No write data for instruction memory
        .rdata(instruction) // Read instruction
    );

    // Instantiate the register file
    register_file reg_file(
        .clk(clk),
        .we(reg_write_enable), // Write enable signal
        .raddr1(rs1_addr), // Read address 1
        .raddr2(rs2_addr), // Read address 2
        .waddr(rd_addr), // Write address
        .wdata(rd_data), // Write data
        .rdata1(rs1_data), // Read data 1
        .rdata2(rs2_data)  // Read data 2
    );

    // Multiplexor for ALU second operand
    assign alu_a = rs1_data;
    assign alu_b = alu_src ? imm : rs2_data;

    // Instantiate the ALU
    alu alu_unit(
        .a(alu_a),
        .b(alu_b),
        .alu_control(alu_control),
        .result(alu_result),
        .zero(alu_zero)
    );

    // Instantiate the data memory
    memory data_memory(
        .clk(clk),
        .mem_read(mem_read_enable), // Memory read enable
        .mem_write(mem_write_enable), // Memory write enable
        .addr(alu_result), // Memory address (from ALU result)
        .wdata(rs2_data), // Memory write data (from rs2)
        .rdata(mem_rdata) // Memory read data
    );

    // parameter for opcodes
    parameter OPCODE_LOAD   = 7'b0000011; // Load instructions
    parameter OPCODE_STORE  = 7'b0100011; // Store instructions
    parameter OPCODE_ARITH  = 7'b0010011; // Arithmetic instructions
    parameter OPCODE_BRANCH = 7'b1100011; // Branch instructions
    parameter OPCODE_JAL    = 7'b1101111; // JAL instruction
    parameter OPCODE_JALR   = 7'b1100111; // JALR instruction
    parameter OPCODE_LUI    = 7'b0110111; // Less Immediate Upper Immediate
    parameter OPCODE_AUIPC  = 7'b0010111; // Add Upper Immediate to pc_jalr
    parameter OPCODE_R_TYPE = 7'b0110011; // R-type instructions

    // Instruction decode
    assign funct7   = instruction[31:25]; // funct7
    assign rs2_addr = instruction[24:20]; // rs2 address
    assign rs1_addr = instruction[19:15]; // rs1 address
    assign funct3   = instruction[14:12]; // funct3
    assign rd_addr  = instruction[11:7]; // rd address
    assign opcode   = instruction[6:0]; // opcode
    

    // immediate extraction
    always_comb begin
        case (opcode) // opcode
            OPCODE_LOAD:   imm = {{21{instruction[31]}}, instruction[30:20]}; // I-immediate value for load instructions (I-type)
            OPCODE_STORE:  imm = {{21{instruction[31]}}, instruction[30:25], instruction[11:7]}; // S-immediate value for store instructions (S-type)
            OPCODE_ARITH:  imm = {{21{instruction[31]}}, instruction[30:20]}; // I-immediate value for arithmetic instructions (I-type)
            OPCODE_BRANCH: imm = {{20{instruction[31]}}, instruction[7], instruction[30:25], instruction[11:8], 1'b0}; // B-immediate value for branch instructions (B-type)
            OPCODE_JAL:    imm = {{12{instruction[31]}}, instruction[19:12], instruction[20], instruction[30:21], 1'b0}; // J-immediate value for JAL (J-type)
            OPCODE_JALR:   imm = {{21{instruction[31]}}, instruction[30:20]}; // I-immediate value for JALR (I-type)
            OPCODE_LUI:    imm = {instruction[31:12], 12'b0}; // immediate value for LUI (U-type)
            OPCODE_AUIPC:  imm = {instruction[31:12], 12'b0}; // immediate value for AUIPC (U-type)
            default: imm = 32'b0; // Default case
        endcase
    end

    // ALU control logic
    always_comb begin
        case (alu_op)
            2'b00: alu_control = 4'b0010; // ADD for load/store
            2'b01: alu_control = 4'b0110; // SUB for branch
            2'b10: begin // R-type or I-type arithmetic
                case (funct3)
                    3'b000: alu_control = (funct7 == 7'b0100000) ? 4'b0110 : 4'b0010; // SUB or ADD
                    3'b111: alu_control = 4'b0000; // AND
                    3'b110: alu_control = 4'b0001; // OR
                    3'b010: alu_control = 4'b0111; // SLT
                    3'b100: alu_control = 4'b1100; // NOR
                    default: alu_control = 4'b0000; // Default case
                endcase
            end 
            default: alu_control = 4'b0000; // Default case
        endcase
    end 

    // Control logic
    always_comb begin
        // Default values 
        alu_src = 1'b0;
        mem_to_reg = 1'b0;
        reg_write_enable = 1'b0;
        mem_read_enable = 1'b0;
        mem_write_enable = 1'b0;
        branch = 1'b0;
        alu_op = 2'b00;
        
        case(opcode)
            OPCODE_LOAD: begin
                alu_src = 1'b1;
                mem_to_reg = 1'b1;
                reg_write_enable = 1'b1;
                mem_read_enable = 1'b1;
                mem_write_enable = 1'b0;
                branch = 1'b0;
                alu_op = 2'b00; // ADD operation
            end 
            OPCODE_STORE: begin
                alu_src = 1'b1;
                mem_to_reg = 1'bx; // Don't care
                reg_write_enable = 1'b0;
                mem_read_enable = 1'b0;
                mem_write_enable = 1'b1;
                branch = 1'b0;
                alu_op = 2'b00; // ADD operation
            end
            OPCODE_ARITH: begin
                alu_src = 1'b1;
                mem_to_reg = 1'b0;
                reg_write_enable = 1'b1;
                mem_read_enable = 1'b0;
                mem_write_enable = 1'b0;
                branch = 1'b0;
                alu_op = 2'b10; // R-type or I-type arithmetic
            end 
            OPCODE_BRANCH: begin
                alu_src = 1'b0;
                mem_to_reg = 1'bx; // Don't care
                reg_write_enable = 1'b0;
                mem_read_enable = 1'b0;
                mem_write_enable = 1'b0;
                branch = 1'b1;
                alu_op = 2'b01; // SUB operation
            end
            OPCODE_R_TYPE: begin
                alu_src = 1'b0;
                mem_to_reg = 1'b0;
                reg_write_enable = 1'b1;
                mem_read_enable = 1'b0;
                mem_write_enable = 1'b0;
                branch = 1'b0;
                alu_op = 2'b10; // R-type arithmetic
            end
            OPCODE_JAL: begin
                alu_src = 1'bx; // Don't care
                mem_to_reg = 1'b0;
                reg_write_enable = 1'b1;
                mem_read_enable = 1'b0;
                mem_write_enable = 1'b0;
                branch = 1'bx; // Don't care
                alu_op = 2'bxx;
            end
            OPCODE_JALR: begin
                alu_src = 1'bx; // Don't care
                mem_to_reg = 1'b0;
                reg_write_enable = 1'b1;
                mem_read_enable = 1'b0;
                mem_write_enable = 1'b0;
                branch = 1'bx; // Don't care
                alu_op = 2'bxx;
            end
            default: begin
                // Default case: do nothing
            end
        endcase
    end 

    // Multiplexor for memory or ALU result to write back to register
    always_comb begin
        case (opcode)
            OPCODE_JAL, OPCODE_JALR: rd_data = pc_plus4; // For JAL and JALR, write PC + 4 to rd
            default: rd_data = mem_to_reg ? mem_rdata : alu_result;
        endcase
    end

    // Add more branch conditions
    logic branch_taken;
    always_comb begin
        branch_taken = 1'b0;
        if (branch) begin
            case (funct3)
                3'b000: branch_taken = alu_zero;  // BEQ: branch if equal (zero flag set)
                3'b001: branch_taken = ~alu_zero; // BNE: branch if not equal (zero flag clear)
                3'b100: branch_taken = alu_result[31]; // BLT: branch if less than 
                3'b101: branch_taken = alu_zero | ~alu_result[31]; // BGE: branch if greater or equal 
                default: branch_taken = 1'b0;
            endcase
        end 
    end 

    // PC logic
    assign pc_branch = pc + imm;
    assign pc_plus4 = pc + 32'd4;

    always_comb begin 
        case (opcode)
            OPCODE_JAL: pc_next = pc_branch; // JAL
            OPCODE_JALR: pc_next = (rs1_data + imm) & ~32'b1; // JALR
            default: pc_next = branch_taken ? pc_branch : pc_plus4; // Branch or next instruction
        endcase
    end   
    // PC register
    always_ff @(posedge clk) begin
        if (reset) begin
            pc <= 32'b0; // Reset PC to 0
        end else begin
            pc <= pc_next; // Update PC
        end
    end


endmodule

sim.vcd
$version Generated by VerilatedVcd $end
$timescale 1ps $end
 $scope module TOP $end
  $var wire 1 b clk $end
  $var wire 1 c reset $end
  $scope module cpu $end
   $var wire 1 b clk $end
   $var wire 1 c reset $end
   $var wire 32 & pc [31:0] $end
   $var wire 32 ' pc_plus4 [31:0] $end
   $var wire 32 ( pc_branch [31:0] $end
   $var wire 32 ) pc_next [31:0] $end
   $var wire 32 * instruction [31:0] $end
   $var wire 1 + reg_write_enable $end
   $var wire 5 , rs1_addr [4:0] $end
   $var wire 5 - rs2_addr [4:0] $end
   $var wire 5 . rd_addr [4:0] $end
   $var wire 32 / rs1_data [31:0] $end
   $var wire 32 0 rs2_data [31:0] $end
   $var wire 32 1 rd_data [31:0] $end
   $var wire 32 / alu_a [31:0] $end
   $var wire 32 2 alu_b [31:0] $end
   $var wire 4 3 alu_control [3:0] $end
   $var wire 32 4 alu_result [31:0] $end
   $var wire 1 5 alu_zero $end
   $var wire 1 6 mem_read_enable $end
   $var wire 1 7 mem_write_enable $end
   $var wire 32 8 mem_rdata [31:0] $end
   $var wire 1 9 branch $end
   $var wire 1 : mem_to_reg $end
   $var wire 2 ; alu_op [1:0] $end
   $var wire 1 < alu_src $end
   $var wire 32 = imm [31:0] $end
   $var wire 7 > opcode [6:0] $end
   $var wire 3 ? funct3 [2:0] $end
   $var wire 7 @ funct7 [6:0] $end
   $var wire 7 d OPCODE_LOAD [6:0] $end
   $var wire 7 e OPCODE_STORE [6:0] $end
   $var wire 7 f OPCODE_ARITH [6:0] $end
   $var wire 7 g OPCODE_BRANCH [6:0] $end
   $var wire 7 h OPCODE_JAL [6:0] $end
   $var wire 7 i OPCODE_JALR [6:0] $end
   $var wire 7 j OPCODE_LUI [6:0] $end
   $var wire 7 k OPCODE_AUIPC [6:0] $end
   $var wire 7 l OPCODE_R_TYPE [6:0] $end
   $var wire 1 A branch_taken $end
   $scope module alu_unit $end
    $var wire 32 / a [31:0] $end
    $var wire 32 2 b [31:0] $end
    $var wire 4 3 alu_control [3:0] $end
    $var wire 32 4 result [31:0] $end
    $var wire 1 5 zero $end
    $var wire 4 m ALU_AND [3:0] $end
    $var wire 4 n ALU_OR [3:0] $end
    $var wire 4 o ALU_ADD [3:0] $end
    $var wire 4 p ALU_SUB [3:0] $end
    $var wire 4 q ALU_SLT [3:0] $end
    $var wire 4 r ALU_NOR [3:0] $end
   $upscope $end
   $scope module data_memory $end
    $var wire 1 b clk $end
    $var wire 1 6 mem_read $end
    $var wire 1 7 mem_write $end
    $var wire 32 4 addr [31:0] $end
    $var wire 32 0 wdata [31:0] $end
    $var wire 32 8 rdata [31:0] $end
    $scope module unnamedblk1 $end
     $var wire 32 # i [31:0] $end
    $upscope $end
   $upscope $end
   $scope module instruction_memory $end
    $var wire 1 b clk $end
    $var wire 1 s mem_read $end
    $var wire 1 t mem_write $end
    $var wire 32 & addr [31:0] $end
    $var wire 32 u wdata [31:0] $end
    $var wire 32 * rdata [31:0] $end
    $scope module unnamedblk1 $end
     $var wire 32 $ i [31:0] $end
    $upscope $end
   $upscope $end
   $scope module reg_file $end
    $var wire 1 b clk $end
    $var wire 1 + we $end
    $var wire 5 , raddr1 [4:0] $end
    $var wire 5 - raddr2 [4:0] $end
    $var wire 5 . waddr [4:0] $end
    $var wire 32 1 wdata [31:0] $end
    $var wire 32 / rdata1 [31:0] $end
    $var wire 32 0 rdata2 [31:0] $end
    $var wire 32 B registers[0] [31:0] $end
    $var wire 32 C registers[1] [31:0] $end
    $var wire 32 D registers[2] [31:0] $end
    $var wire 32 E registers[3] [31:0] $end
    $var wire 32 F registers[4] [31:0] $end
    $var wire 32 G registers[5] [31:0] $end
    $var wire 32 H registers[6] [31:0] $end
    $var wire 32 I registers[7] [31:0] $end
    $var wire 32 J registers[8] [31:0] $end
    $var wire 32 K registers[9] [31:0] $end
    $var wire 32 L registers[10] [31:0] $end
    $var wire 32 M registers[11] [31:0] $end
    $var wire 32 N registers[12] [31:0] $end
    $var wire 32 O registers[13] [31:0] $end
    $var wire 32 P registers[14] [31:0] $end
    $var wire 32 Q registers[15] [31:0] $end
    $var wire 32 R registers[16] [31:0] $end
    $var wire 32 S registers[17] [31:0] $end
    $var wire 32 T registers[18] [31:0] $end
    $var wire 32 U registers[19] [31:0] $end
    $var wire 32 V registers[20] [31:0] $end
    $var wire 32 W registers[21] [31:0] $end
    $var wire 32 X registers[22] [31:0] $end
    $var wire 32 Y registers[23] [31:0] $end
    $var wire 32 Z registers[24] [31:0] $end
    $var wire 32 [ registers[25] [31:0] $end
    $var wire 32 \ registers[26] [31:0] $end
    $var wire 32 ] registers[27] [31:0] $end
    $var wire 32 ^ registers[28] [31:0] $end
    $var wire 32 _ registers[29] [31:0] $end
    $var wire 32 ` registers[30] [31:0] $end
    $var wire 32 a registers[31] [31:0] $end
    $var wire 32 % i [31:0] $end
   $upscope $end
  $upscope $end
 $upscope $end
$enddefinitions $end


#0
b00000000000000000000100000000000 #
b00000000000000000000100000000000 $
b00000000000000000000000000100000 %
b00000000000000000000000000000000 &
b00000000000000000000000000000100 '
b00000000000000000000000000000100 (
b00000000000000000000000000000100 )
b00000000010000000000000001101111 *
1+
b00000 ,
b00100 -
b00000 .
b00000000000000000000000000000000 /
b00000000000000000000000000000000 0
b00000000000000000000000000000100 1
b00000000000000000000000000000000 2
b0010 3
b00000000000000000000000000000000 4
15
06
07
b00000000000000000000000000000000 8
09
0:
b00 ;
0<
b00000000000000000000000000000100 =
b1101111 >
b000 ?
b0000000 @
0A
b00000000000000000000000000000000 B
b00000000000000000000000000000000 C
b00000000000000001000000000000000 D
b00000000000000000000000000000000 E
b00000000000000000000000000000000 F
b00000000000000000000000000000000 G
b00000000000000000000000000000000 H
b00000000000000000000000000000000 I
b00000000000000000000000000000000 J
b00000000000000000000000000000000 K
b00000000000000000000000000000000 L
b00000000000000000000000000000000 M
b00000000000000000000000000000000 N
b00000000000000000000000000000000 O
b00000000000000000000000000000000 P
b00000000000000000000000000000000 Q
b00000000000000000000000000000000 R
b00000000000000000000000000000000 S
b00000000000000000000000000000000 T
b00000000000000000000000000000000 U
b00000000000000000000000000000000 V
b00000000000000000000000000000000 W
b00000000000000000000000000000000 X
b00000000000000000000000000000000 Y
b00000000000000000000000000000000 Z
b00000000000000000000000000000000 [
b00000000000000000000000000000000 \
b00000000000000000000000000000000 ]
b00000000000000000000000000000000 ^
b00000000000000000000000000000000 _
b00000000000000000000000000000000 `
b00000000000000000000000000000000 a
1b
1c
b0000011 d
b0100011 e
b0010011 f
b1100011 g
b1101111 h
b1100111 i
b0110111 j
b0010111 k
b0110011 l
b0000 m
b0001 n
b0010 o
b0110 p
b0111 q
b1100 r
1s
0t
b00000000000000000000000000000000 u
#5
0b
#10
1b
#15
0b
#20
1b
#25
0b
#30
1b
#35
0b
#40
1b
#45
0b
#50
1b
#55
0b
#60
1b
#65
0b
#70
1b
#75
0b
#80
1b
#85
0b
#90
1b
#95
0b
#100
b00000000000000000000000000000100 &
b00000000000000000000000000001000 '
b11111111111111111111111111100100 (
b00000000000000000000000000001000 )
b11111110000000010000000100010011 *
b00010 ,
b00000 -
b00010 .
b00000000000000001000000000000000 /
b00000000000000000111111111100000 1
b11111111111111111111111111100000 2
b00000000000000000111111111100000 4
05
b10 ;
1<
b11111111111111111111111111100000 =
b0010011 >
b1111111 @
1b
0c
#105
0b
#110
b00000000000000000000000000001000 &
b00000000000000000000000000001100 '
b00000000000000000000000000100100 (
b00000000000000000000000000001100 )
b00000000000100010010111000100011 *
0+
b00001 -
b11100 .
b00000000000000000111111111100000 /
b00000000000000000111111111111100 1
b00000000000000000000000000011100 2
b00000000000000000111111111111100 4
17
b00 ;
b00000000000000000000000000011100 =
b0100011 >
b010 ?
b0000000 @
b00000000000000000111111111100000 D
1b
#115
0b
#120
b00000000000000000000000000001100 &
b00000000000000000000000000010000 '
b00000000000000000000000000010000 )
b00000000100000010010110000100011 *
b01000 -
b11000 .
b00000000000000000111111111111000 1
b00000000000000000000000000011000 2
b00000000000000000111111111111000 4
b00000000000000000000000000011000 =
1b
#125
0b
#130
b00000000000000000000000000010000 &
b00000000000000000000000000010100 '
b00000000000000000000000000110000 (
b00000000000000000000000000010100 )
b00000010000000010000010000010011 *
1+
b00000 -
b01000 .
b00000000000000001000000000000000 1
b00000000000000000000000000100000 2
b00000000000000001000000000000000 4
07
b10 ;
b00000000000000000000000000100000 =
b0010011 >
b000 ?
b0000001 @
1b
#135
0b
#140
b00000000000000000000000000010100 &
b00000000000000000000000000011000 '
b00000000000000000000000000000000 (
b00000000000000000000000000011000 )
b11111110000001000010011000100011 *
0+
b01000 ,
b01100 .
b00000000000000001000000000000000 /
b00000000000000000111111111101100 1
b11111111111111111111111111101100 2
b00000000000000000111111111101100 4
17
b00 ;
b11111111111111111111111111101100 =
b0100011 >
b010 ?
b1111111 @
b00000000000000001000000000000000 J
1b
#145
0b
#150
b00000000000000000000000000011000 &
b00000000000000000000000000011100 '
b00000000000000000000000000011001 (
b00000000000000000000000000011100 )
b00000000000100000000011110010011 *
1+
b00000 ,
b00001 -
b01111 .
b00000000000000000000000000000000 /
b00000000000000000000000000000001 1
b00000000000000000000000000000001 2
b00000000000000000000000000000001 4
07
b10 ;
b00000000000000000000000000000001 =
b0010011 >
b000 ?
b0000000 @
1b
#155
0b
#160
b00000000000000000000000000011100 &
b00000000000000000000000000100000 '
b00000000000000000000000000000100 (
b00000000000000000000000000100000 )
b11111110111101000010010000100011 *
0+
b01000 ,
b01111 -
b01000 .
b00000000000000001000000000000000 /
b00000000000000000000000000000001 0
b00000000000000000111111111101000 1
b11111111111111111111111111101000 2
b00000000000000000111111111101000 4
17
b00 ;
b11111111111111111111111111101000 =
b0100011 >
b010 ?
b1111111 @
b00000000000000000000000000000001 Q
1b
#165
0b
#170
b00000000000000000000000000100000 &
b00000000000000000000000000100100 '
b00000000000000000000000001000000 (
b00000000000000000000000001000000 )
b00000010000000000000000001101111 *
1+
b00000 ,
b00000 -
b00000 .
b00000000000000000000000000000000 /
b00000000000000000000000000000000 0
b00000000000000000000000000100100 1
b00000000000000000000000000000000 2
b00000000000000000000000000000000 4
15
07
0<
b00000000000000000000000000100000 =
b1101111 >
b000 ?
b0000001 @
1b
#175
0b
#180
b00000000000000000000000001000000 &
b00000000000000000000000001000100 '
b00000000000000000000000000101000 (
b00000000000000000000000001000100 )
b11111110100001000010011100000011 *
b01000 ,
b01000 -
b01110 .
b00000000000000001000000000000000 /
b00000000000000001000000000000000 0
b00000000000000000000000000000001 1
b11111111111111111111111111101000 2
b00000000000000000111111111101000 4
05
16
b00000000000000000000000000000001 8
1:
1<
b11111111111111111111111111101000 =
b0000011 >
b010 ?
b1111111 @
1b
#185
0b
#190
b00000000000000000000000001000100 &
b00000000000000000000000001001000 '
b00000000000000000000000001001110 (
b00000000000000000000000001001000 )
b00000000101000000000011110010011 *
b00000 ,
b01010 -
b01111 .
b00000000000000000000000000000000 /
b00000000000000000000000000000000 0
b00000000000000000000000000001010 1
b00000000000000000000000000001010 2
b00000000000000000000000000001010 4
06
b00000000000000000000000000000000 8
0:
b10 ;
b00000000000000000000000000001010 =
b0010011 >
b000 ?
b0000000 @
b00000000000000000000000000000001 P
1b
#195
0b
#200
b00000000000000000000000001001000 &
b00000000000000000000000001001100 '
b00000000000000000000000000100100 (
b00000000000000000000000000100100 )
b11111100111001111101111011100011 *
0+
b01111 ,
b01110 -
b11101 .
b00000000000000000000000000001010 /
b00000000000000000000000000000001 0
b00000000000000000000000000001001 1
b00000000000000000000000000000001 2
b0110 3
b00000000000000000000000000001001 4
19
b01 ;
0<
b11111111111111111111111111011100 =
b1100011 >
b101 ?
b1111110 @
1A
b00000000000000000000000000001010 Q
1b
#205
0b
#210
b00000000000000000000000000100100 &
b00000000000000000000000000101000 '
b00000000000000000000000000010000 (
b00000000000000000000000000101000 )
b11111110110001000010011100000011 *
1+
b01000 ,
b01100 -
b01110 .
b00000000000000001000000000000000 /
b00000000000000000000000000000000 0
b00000000000000000000000000000000 1
b11111111111111111111111111101100 2
b0010 3
b00000000000000000111111111101100 4
16
09
1:
b00 ;
1<
b11111111111111111111111111101100 =
b0000011 >
b010 ?
b1111111 @
0A
1b
#215
0b
#220
b00000000000000000000000000101000 &
b00000000000000000000000000101100 '
b00000000000000000000000000101100 )
b11111110100001000010011110000011 *
b01000 -
b01111 .
b00000000000000001000000000000000 0
b00000000000000000000000000000001 1
b11111111111111111111111111101000 2
b00000000000000000111111111101000 4
b00000000000000000000000000000001 8
b11111111111111111111111111101000 =
b00000000000000000000000000000000 P
1b
#225
0b
#230
b00000000000000000000000000101100 &
b00000000000000000000000000110000 '
b00000000000000000000000000101100 (
b00000000000000000000000000110000 )
b00000000111101110000011110110011 *
b01110 ,
b01111 -
b00000000000000000000000000000000 /
b00000000000000000000000000000001 0
b00000000000000000000000000000001 2
b00000000000000000000000000000001 4
06
b00000000000000000000000000000000 8
0:
b10 ;
0<
b00000000000000000000000000000000 =
b0110011 >
b000 ?
b0000000 @
b00000000000000000000000000000001 Q
1b
#235
0b
#240
b00000000000000000000000000110000 &
b00000000000000000000000000110100 '
b00000000000000000000000000011100 (
b00000000000000000000000000110100 )
b11111110111101000010011000100011 *
0+
b01000 ,
b01100 .
b00000000000000001000000000000000 /
b00000000000000000111111111101100 1
b11111111111111111111111111101100 2
b00000000000000000111111111101100 4
17
b00 ;
1<
b11111111111111111111111111101100 =
b0100011 >
b010 ?
b1111111 @
1b
#245
0b
#250
b00000000000000000000000000110100 &
b00000000000000000000000000111000 '
b00000000000000000000000000111000 )
b11111110100001000010011110000011 *
1+
b01000 -
b01111 .
b00000000000000001000000000000000 0
b00000000000000000000000000000001 1
b11111111111111111111111111101000 2
b00000000000000000111111111101000 4
16
07
b00000000000000000000000000000001 8
1:
b11111111111111111111111111101000 =
b0000011 >
1b
#255
0b
#260
b00000000000000000000000000111000 &
b00000000000000000000000000111100 '
b00000000000000000000000000111001 (
b00000000000000000000000000111100 )
b00000000000101111000011110010011 *
b01111 ,
b00001 -
b00000000000000000000000000000001 /
b00000000000000000000000000000000 0
b00000000000000000000000000000010 1
b00000000000000000000000000000001 2
b00000000000000000000000000000010 4
06
b00000000000000000000000000000000 8
0:
b10 ;
b00000000000000000000000000000001 =
b0010011 >
b000 ?
b0000000 @
1b
#265
0b
#270
b00000000000000000000000000111100 &
b00000000000000000000000001000000 '
b00000000000000000000000000100100 (
b00000000000000000000000001000000 )
b11111110111101000010010000100011 *
0+
b01000 ,
b01111 -
b01000 .
b00000000000000001000000000000000 /
b00000000000000000000000000000010 0
b00000000000000000111111111101000 1
b11111111111111111111111111101000 2
b00000000000000000111111111101000 4
17
b00 ;
b11111111111111111111111111101000 =
b0100011 >
b010 ?
b1111111 @
b00000000000000000000000000000010 Q
1b
#275
0b
#280
b00000000000000000000000001000000 &
b00000000000000000000000001000100 '
b00000000000000000000000000101000 (
b00000000000000000000000001000100 )
b11111110100001000010011100000011 *
1+
b01000 -
b01110 .
b00000000000000001000000000000000 0
b00000000000000000000000000000010 1
16
07
b00000000000000000000000000000010 8
1:
b0000011 >
1b
#285
0b
#290
b00000000000000000000000001000100 &
b00000000000000000000000001001000 '
b00000000000000000000000001001110 (
b00000000000000000000000001001000 )
b00000000101000000000011110010011 *
b00000 ,
b01010 -
b01111 .
b00000000000000000000000000000000 /
b00000000000000000000000000000000 0
b00000000000000000000000000001010 1
b00000000000000000000000000001010 2
b00000000000000000000000000001010 4
06
b00000000000000000000000000000000 8
0:
b10 ;
b00000000000000000000000000001010 =
b0010011 >
b000 ?
b0000000 @
b00000000000000000000000000000010 P
1b
#295
0b
#300
b00000000000000000000000001001000 &
b00000000000000000000000001001100 '
b00000000000000000000000000100100 (
b00000000000000000000000000100100 )
b11111100111001111101111011100011 *
0+
b01111 ,
b01110 -
b11101 .
b00000000000000000000000000001010 /
b00000000000000000000000000000010 0
b00000000000000000000000000001000 1
b00000000000000000000000000000010 2
b0110 3
b00000000000000000000000000001000 4
19
b01 ;
0<
b11111111111111111111111111011100 =
b1100011 >
b101 ?
b1111110 @
1A
b00000000000000000000000000001010 Q
1b
#305
0b
#310
b00000000000000000000000000100100 &
b00000000000000000000000000101000 '
b00000000000000000000000000010000 (
b00000000000000000000000000101000 )
b11111110110001000010011100000011 *
1+
b01000 ,
b01100 -
b01110 .
b00000000000000001000000000000000 /
b00000000000000000000000000000000 0
b00000000000000000000000000000001 1
b11111111111111111111111111101100 2
b0010 3
b00000000000000000111111111101100 4
16
b00000000000000000000000000000001 8
09
1:
b00 ;
1<
b11111111111111111111111111101100 =
b0000011 >
b010 ?
b1111111 @
0A
1b
#315
0b
#320
b00000000000000000000000000101000 &
b00000000000000000000000000101100 '
b00000000000000000000000000101100 )
b11111110100001000010011110000011 *
b01000 -
b01111 .
b00000000000000001000000000000000 0
b00000000000000000000000000000010 1
b11111111111111111111111111101000 2
b00000000000000000111111111101000 4
b00000000000000000000000000000010 8
b11111111111111111111111111101000 =
b00000000000000000000000000000001 P
1b
#325
0b
#330
b00000000000000000000000000101100 &
b00000000000000000000000000110000 '
b00000000000000000000000000101100 (
b00000000000000000000000000110000 )
b00000000111101110000011110110011 *
b01110 ,
b01111 -
b00000000000000000000000000000001 /
b00000000000000000000000000000010 0
b00000000000000000000000000000011 1
b00000000000000000000000000000010 2
b00000000000000000000000000000011 4
06
b00000000000000000000000000000000 8
0:
b10 ;
0<
b00000000000000000000000000000000 =
b0110011 >
b000 ?
b0000000 @
b00000000000000000000000000000010 Q
1b
#335
0b
#340
b00000000000000000000000000110000 &
b00000000000000000000000000110100 '
b00000000000000000000000000011100 (
b00000000000000000000000000110100 )
b11111110111101000010011000100011 *
0+
b01000 ,
b01100 .
b00000000000000001000000000000000 /
b00000000000000000000000000000011 0
b00000000000000000111111111101100 1
b11111111111111111111111111101100 2
b00000000000000000111111111101100 4
17
b00 ;
1<
b11111111111111111111111111101100 =
b0100011 >
b010 ?
b1111111 @
b00000000000000000000000000000011 Q
1b
#345
0b
